{
    "title": "春の卓球教室開催のお知らせ",
    "description": "若葉台地区センターで行われる卓球教室のご案内です。",
    "tts": "nijivoice",
    "speed": "0.82",
    "voices": [
      "311a59fa-01b2-4d2e-9968-10d2034f8f86",
      "249d8d02-2c25-4a24-8faf-26d6f734b7bc"
    ],
    "charactors": ["有馬 慎一郎", "蘭華"],
    "speakers": ["朝陽", "若葉"],
    "script": [
      {
        "speaker": "朝陽",
        "text": "若葉台地区センターのホームページから、春の卓球教室の開催のお知らせです。"
      },
      {
        "speaker": "若葉",
        "text": "4月12日の土曜日、若葉台地区センターの体育室にて、卓球教室が開催されます。春の訪れとともに、体を動かしてリフレッシュできる良い機会ですね。"
      },
      {
        "speaker": "朝陽",
        "text": "講師は、井関英生さんです。卓球マシンを活用した指導が特徴です。初心者のかたには基本から、経験者のかたにはステップアップの練習ができる内容となっています。"
      },
      {
        "speaker": "若葉",
        "text": "対象は小学生以上の方です。小学生の皆さんには、反射神経や集中力を養う絶好のチャンスとなりますね。また、中高年の方々にとっても、適度な運動で、健康維持や脳の活性化につながります。年配の方も無理なく楽しめるスポーツですので、どの年代の方もぜひお気軽にご参加ください。"
      },
      {
        "speaker": "朝陽",
        "text": "参加費は500円です。そして小学生は特別価格の200円となっています。"
      },
      {
        "speaker": "若葉",
        "text": "定員は15名の少人数制で、一人ひとりに丁寧な指導が受けられます。待ち時間も空いている卓球台で自由に練習できますので、無駄がないのも魅力です。"
      },
      {
        "speaker": "朝陽",
        "text": "時間は午後3時から5時までの2時間。春の心地よい午後にぴったりの活動ですね。"
      },
      {
        "speaker": "若葉",
        "text": "持ち物は室内履きとラケットです。お忘れなくご準備ください。"
      },
      {
        "speaker": "朝陽",
        "text": "申し込みは当日、開始15分前の、2時45分から、会場で受付開始となります。"
      },
      {
        "speaker": "若葉",
        "text": "ご家族やご友人との参加も大歓迎です。運動不足の解消や、ストレス発散、新しい趣味の発見にもつながりますよ。"
      },
      {
        "speaker": "朝陽",
        "text": "地域のかたとの交流の場としてもおすすめです。詳しくは、若葉台地区センターまでお問い合わせください。"
      },
      {
        "speaker": "若葉",
        "text": "4月12日土曜日に開催される、春の卓球教室のご案内でした。この情報は、若葉台地区センターのホームページでもご確認いただけます"
      }
    ]
  }
  