{
    "title": "こども食堂ポピーのご案内",
    "description": "若葉台地区センターで開催されるこども食堂ポピーについての会話",
    "tts": "nijivoice",
    "cache": false,
    "speed": "0.82",
    "voices": [
      "311a59fa-01b2-4d2e-9968-10d2034f8f86",
      "249d8d02-2c25-4a24-8faf-26d6f734b7bc"
    ],
    "charactors": ["有馬 慎一郎", "蘭華"],
    "speakers": ["朝陽", "若葉"],
    "script": [
      {
        "speaker": "朝陽",
        "text": "若葉台、地区センターで、こども食堂ポピーが開催されるそうですよ。"
      },
      {
        "speaker": "若葉",
        "text": "そうなんですね！地域の皆さんに親しまれているイベントですよね。"
      },
      {
        "speaker": "朝陽",
        "text": "そうです。次回の開催日は、2月16日の日曜日と、3月2日の日曜日です。"
      },
      {
        "speaker": "若葉",
        "text": "時間は何時からですか？"
      },
      {
        "speaker": "朝陽",
        "text": "午前11時から午後2時までです。"
      },
      {
        "speaker": "若葉",
        "text": "子どもたちは無料で食事ができるんですよね？"
      },
      {
        "speaker": "朝陽",
        "text": "はい、高校生までの子どもは無料です。"
      },
      {
        "speaker": "若葉",
        "text": "大人のかたは300円で食事ができるんですよね？"
      },
      {
        "speaker": "朝陽",
        "text": "はい！どなたでも参加できるので、親子や地域の方々との交流の場としてもおすすめです。"
      },
      {
        "speaker": "若葉",
        "text": "どんなメニューが出るんでしょう？"
      },
      {
        "speaker": "朝陽",
        "text": "それは当日のお楽しみです。何が出るのかワクワクしますね。"
      },
      {
        "speaker": "若葉",
        "text": "手作りの温かい食事が楽しめるのは魅力的ですね。"
      },
      {
        "speaker": "朝陽",
        "text": "どなたでも参加OKですよ。"
      },
      {
        "speaker": "若葉",
        "text": "一人でも、お友達や家族と一緒でも気軽に参加できますね。"
      },
      {
        "speaker": "朝陽",
        "text": "そうです。みんなで楽しく食事をしましょう。"
      },
      {
        "speaker": "若葉",
        "text": "ただ、食事はなくなり次第終了なんですよね？"
      },
      {
        "speaker": "朝陽",
        "text": "その通りです。早めに行くのがおすすめですよ。"
      },
      {
        "speaker": "若葉",
        "text": "アレルギー対応はありますか？"
      },
      {
        "speaker": "朝陽",
        "text": "可能な範囲で対応しているそうです。気になる方は事前に確認してください。"
      },
      {
        "speaker": "若葉",
        "text": "温かい食事と交流の場、素敵ですね。"
      },
      {
        "speaker": "朝陽",
        "text": "ぜひ興味のある方は足を運んでみてくださいね！"
      },
      {
        "speaker": "若葉",
        "text": "最後にもう一度、イベントの詳細です。"
      },
      {
        "speaker": "朝陽",
        "text": "2月16日の日曜日と、3月2日の日曜日の11時から2時まで。こども食堂ポピーが地区センターで開催されます。"
      },
      {
        "speaker": "若葉",
        "text": "こちらの情報は、若葉台コミュニティラジオのホームページでもご確認頂けます。"
      }
    ]
  }
  